exllamav3/__init__.py
exllamav3/constants.py
exllamav3/ext.py
exllamav3/model_init.py
exllamav3/version.py
exllamav3/architecture/__init__.py
exllamav3/architecture/apertus.py
exllamav3/architecture/arcee.py
exllamav3/architecture/architectures.py
exllamav3/architecture/cohere.py
exllamav3/architecture/cohere2.py
exllamav3/architecture/decilm.py
exllamav3/architecture/dots1.py
exllamav3/architecture/ernie4_5.py
exllamav3/architecture/ernie4_5_moe.py
exllamav3/architecture/exaone4.py
exllamav3/architecture/gemma2.py
exllamav3/architecture/gemma3.py
exllamav3/architecture/glm4.py
exllamav3/architecture/glm4_moe.py
exllamav3/architecture/glm4v.py
exllamav3/architecture/glm4v_moe.py
exllamav3/architecture/hcxvisionv2.py
exllamav3/architecture/hyperclovax.py
exllamav3/architecture/iquestcoder.py
exllamav3/architecture/llama.py
exllamav3/architecture/mimo.py
exllamav3/architecture/minimax_m2.py
exllamav3/architecture/ministral3.py
exllamav3/architecture/mistral.py
exllamav3/architecture/mistral3.py
exllamav3/architecture/mixtral.py
exllamav3/architecture/nanochat.py
exllamav3/architecture/olmo3.py
exllamav3/architecture/phi3.py
exllamav3/architecture/qwen2.py
exllamav3/architecture/qwen2_5_vl.py
exllamav3/architecture/qwen3.py
exllamav3/architecture/qwen3_moe.py
exllamav3/architecture/qwen3_next.py
exllamav3/architecture/qwen3_vl.py
exllamav3/architecture/qwen3_vl_moe.py
exllamav3/architecture/seedoss.py
exllamav3/architecture/smollm3.py
exllamav3/architecture/solar_open_moe.py
exllamav3/cache/__init__.py
exllamav3/cache/cache.py
exllamav3/cache/fp16.py
exllamav3/cache/quant.py
exllamav3/cache/recurrent.py
exllamav3/conversion/__init__.py
exllamav3/conversion/allocation.py
exllamav3/conversion/calibration_data.py
exllamav3/conversion/compile.py
exllamav3/conversion/convert_model.py
exllamav3/conversion/measure_model.py
exllamav3/conversion/optimize_model.py
exllamav3/conversion/quant_config.py
exllamav3/conversion/standard_cal_data/__init__.py
exllamav3-0.0.20.dist-info/LICENSE
exllamav3-0.0.20.dist-info/METADATA
exllamav3-0.0.20.dist-info/WHEEL
exllamav3-0.0.20.dist-info/top_level.txt
exllamav3-0.0.20.dist-info/RECORD
