Metadata-Version: 2.1
Name: exllamav3
Version: 0.0.20
Home-page: https://github.com/turboderp/exllamav3
Author: turboderp
License: MIT
License-File: LICENSE
Requires-Dist: torch>=2.6.0
Requires-Dist: flash-attn>=2.7.4.post1
Requires-Dist: tokenizers>=0.21.1
Requires-Dist: numpy>=2.1.0
Requires-Dist: rich
Requires-Dist: typing-extensions
Requires-Dist: ninja
Requires-Dist: safetensors>=0.3.2
Requires-Dist: pyyaml
Requires-Dist: marisa-trie
Requires-Dist: kbnf>=0.4.2
Requires-Dist: formatron>=0.5.0
Requires-Dist: pydantic==2.11.0
